MetaCHIP/BP.py
MetaCHIP/MetaCHIP_add_group_to_tree.R
MetaCHIP/MetaCHIP_circos_HGT.R
MetaCHIP/MetaCHIP_config.py
MetaCHIP/MetaCHIP_phylo.hmm
MetaCHIP/MetaCHIP_phylo_v1.0.0.hmm
MetaCHIP/PI.py
MetaCHIP/Ranger-DTL-Dated.linux
MetaCHIP/Ranger-DTL-Dated.mac
MetaCHIP/SankeyTaxon.py
MetaCHIP/VERSION
MetaCHIP/__init__.py
MetaCHIP/add_group_to_tree.R
MetaCHIP/circos_HGT.py
MetaCHIP/filter_HGT.py
MetaCHIP/get_SCG_tree.py
MetaCHIP/get_flk_gene_functions.py
MetaCHIP/get_sankey_plot.R
MetaCHIP/rename_seqs.py
MetaCHIP/tmp_1.py
MetaCHIP/tmp_2.py
MetaCHIP/tuning_full_length_and_end_match.py
MetaCHIP/update_hmms.py
MetaCHIP-1.10.10.data/scripts/MetaCHIP
MetaCHIP-1.10.10.dist-info/LICENSE.txt
MetaCHIP-1.10.10.dist-info/METADATA
MetaCHIP-1.10.10.dist-info/WHEEL
MetaCHIP-1.10.10.dist-info/top_level.txt
MetaCHIP-1.10.10.dist-info/RECORD
