Metadata-Version: 2.1
Name: MetaCHIP
Version: 1.10.10
Summary: HGT detection pipeline
Home-page: https://github.com/songweizhi/MetaCHIP
Author: Weizhi Song, Torsten Thomas
Author-email: songwz03@gmail.com
License: GPL3+
Keywords: Bioinformatics Metagenomics HGT_detection
Platform: UNKNOWN
Requires-Dist: biopython
Requires-Dist: matplotlib
Requires-Dist: numpy
Requires-Dist: scipy
Requires-Dist: reportlab
Requires-Dist: ete3
